audio_transcriber/__init__.py
audio_transcriber/__main__.py
audio_transcriber/audio_transcriber.py
audio_transcriber/audio_transcriber_agent.py
audio_transcriber/audio_transcriber_mcp.py
audio_transcriber/mcp_config.json
audio_transcriber/middlewares.py
audio_transcriber/utils.py
audio_transcriber/skills/audio-transcriber-audio-processing/SKILL.md
audio_transcriber-0.5.75.dist-info/licenses/LICENSE
audio_transcriber-0.5.75.dist-info/METADATA
audio_transcriber-0.5.75.dist-info/WHEEL
audio_transcriber-0.5.75.dist-info/entry_points.txt
audio_transcriber-0.5.75.dist-info/top_level.txt
audio_transcriber-0.5.75.dist-info/RECORD
