Metadata-Version: 2.4
Name: audio-transcriber
Version: 0.5.75
Summary: Transcribe your .wav .mp4 .mp3 .flac files to text or record your own audio!
Author-email: Audel Rouhi <knucklessg1@gmail.com>
License: MIT
Classifier: Development Status :: 5 - Production/Stable
Classifier: License :: Public Domain
Classifier: Environment :: Console
Classifier: Operating System :: POSIX :: Linux
Classifier: Programming Language :: Python :: 3
Requires-Python: >=3.10
License-File: LICENSE
Requires-Dist: fastmcp>=3.0.0b1
Requires-Dist: pyaudio>=0.2.14
Requires-Dist: openai-whisper>=20250625
Requires-Dist: setuptools-rust>=1.12.0
Provides-Extra: mcp
Requires-Dist: fastmcp>=3.0.0b1; extra == "mcp"
Requires-Dist: eunomia-mcp>=0.3.10; extra == "mcp"
Requires-Dist: fastapi>=0.128.0; extra == "mcp"
Provides-Extra: a2a
Requires-Dist: pydantic-ai-slim[a2a,ag-ui,anthropic,fastmcp,google,huggingface,openai,web]>=1.32.0; extra == "a2a"
Requires-Dist: pydantic-ai-skills; extra == "a2a"
Requires-Dist: fastapi>=0.128.0; extra == "a2a"
Provides-Extra: all
Requires-Dist: fastmcp>=2.13.0.2; extra == "all"
Requires-Dist: eunomia-mcp>=0.3.10; extra == "all"
Requires-Dist: pydantic-ai-slim[a2a,ag-ui,anthropic,fastmcp,google,huggingface,openai,web]>=1.32.0; extra == "all"
Requires-Dist: pydantic-ai-skills; extra == "all"
Requires-Dist: fastapi>=0.128.0; extra == "all"
Dynamic: license-file
